clipboard_to_ping-0.1.2.dist-info/METADATA
clipboard_to_ping-0.1.2.dist-info/WHEEL
clipboard_to_ping-0.1.2.dist-info/entry_points.txt
clipboard_to_ping/__init__.py
clipboard_to_ping/__main__.py
clipboard_to_ping/icon.png
clipboard_to_ping/settings.json
clipboard_to_ping/settings.py
clipboard_to_ping-0.1.2.dist-info/RECORD
